MANIFEST.in
README.rst
setup.py
vimeo/__init__.py
vimeo/advanced.py
vimeo/simple.py
vimeo_wrapper.egg-info/PKG-INFO
vimeo_wrapper.egg-info/SOURCES.txt
vimeo_wrapper.egg-info/dependency_links.txt
vimeo_wrapper.egg-info/requires.txt
vimeo_wrapper.egg-info/top_level.txt