Metadata-Version: 1.0
Name: vimeo-wrapper
Version: 0.4.4
Summary: A thin wrapper around requests for vimeo
Home-page: http://github.com/okke-formsma/vimeo-wrapper
Author: Okke Formsma
Author-email: okke.formsma@gmail.com
License: UNKNOWN
Platform: UNKNOWN
Classifier: Development Status :: 4 - Beta
Classifier: Environment :: Web Environment
Classifier: Intended Audience :: Developers
Classifier: License :: OSI Approved :: MIT License
Classifier: Operating System :: OS Independent
Classifier: Programming Language :: Python
